isn_tractor/__init__.py
isn_tractor/ibisn.py
isn_tractor-0.3.6.dist-info/LICENSE
isn_tractor-0.3.6.dist-info/METADATA
isn_tractor-0.3.6.dist-info/WHEEL
isn_tractor-0.3.6.dist-info/RECORD
