Metadata-Version: 2.1
Name: isn-tractor
Version: 0.3.6
Summary: Interactome based Individual Specific Networks
Home-page: https://github.com/GiadaLalli/ISN-tractor
License: MIT
Author: Giada Lalli
Author-email: giada.lalli@kuleuven.be
Requires-Python: >=3.9,<3.13
Classifier: License :: OSI Approved :: MIT License
Classifier: Programming Language :: Python :: 3
Classifier: Programming Language :: Python :: 3.9
Classifier: Programming Language :: Python :: 3.10
Classifier: Programming Language :: Python :: 3.11
Classifier: Programming Language :: Python :: 3.12
Requires-Dist: numpy (>=2.0.0,<3.0.0)
Requires-Dist: pandas (>=2.2.2,<3.0.0)
Requires-Dist: torch (>=2.3.1,<3.0.0)
Project-URL: Repository, https://github.com/GiadaLalli/ISN-tractor
